METAMCP.md
README.md
adbdevicemanager.py
config.yaml.example
run-mcp-server.sh
server.py
mcp_server_android-0.3.1.dist-info/METADATA
mcp_server_android-0.3.1.dist-info/WHEEL
mcp_server_android-0.3.1.dist-info/entry_points.txt
mcp_server_android-0.3.1.dist-info/licenses/LICENSE
mcp_server_android-0.3.1.dist-info/RECORD
