Metadata-Version: 2.4
Name: mcp-server-android
Version: 0.3.1
Summary: MCP server for Android device automation via ADB
Project-URL: Homepage, https://github.com/minhalvp/android-mcp-server
Project-URL: Repository, https://github.com/minhalvp/android-mcp-server
Project-URL: Issues, https://github.com/minhalvp/android-mcp-server/issues
Project-URL: Documentation, https://github.com/minhalvp/android-mcp-server#readme
Author: minhalvp
License: MIT
License-File: LICENSE
Keywords: adb,android,automation,debugging,mcp,testing
Classifier: Development Status :: 4 - Beta
Classifier: Intended Audience :: Developers
Classifier: License :: OSI Approved :: MIT License
Classifier: Programming Language :: Python :: 3
Classifier: Programming Language :: Python :: 3.11
Classifier: Programming Language :: Python :: 3.12
Requires-Python: >=3.11
Requires-Dist: mcp>=1.13.0
Requires-Dist: pillow>=10.0.0
Requires-Dist: pure-python-adb>=0.3.0.dev0
Requires-Dist: pyyaml>=6.0
Provides-Extra: test
Requires-Dist: pytest-cov>=4.0.0; extra == 'test'
Requires-Dist: pytest-mock>=3.12.0; extra == 'test'
Requires-Dist: pytest>=8.0.0; extra == 'test'
